MANIFEST.in
Makefile
README.rst
setup.py
python_zpar.egg-info/PKG-INFO
python_zpar.egg-info/SOURCES.txt
python_zpar.egg-info/dependency_links.txt
python_zpar.egg-info/entry_points.txt
python_zpar.egg-info/top_level.txt
src/Makefile
src/Makefile.lib.zpar
src/reader.h
src/zpar.lib.cpp
zpar/DepParser.py
zpar/DepParser.pyc
zpar/Parser.py
zpar/Parser.pyc
zpar/Tagger.py
zpar/Tagger.pyc
zpar/__init__.py
zpar/__init__.pyc
zpar/zpar_server.py