Metadata-Version: 1.1
Name: python-zpar
Version: 0.9.5
Summary: A Wrapper around the ZPar statistical tagger/parser for English
Home-page: http://www.github.com/EducationalTestingService/python-zpar
Author: Nitin Madnani
Author-email: nmadnani@ets.org
License: MIT
Platform: UNKNOWN
Classifier: Intended Audience :: Science/Research
Classifier: Intended Audience :: Developers
Classifier: License :: OSI Approved :: MIT License
Classifier: Programming Language :: Python
Classifier: Topic :: Software Development
Classifier: Topic :: Scientific/Engineering
Classifier: Operating System :: POSIX
Classifier: Operating System :: Unix
Classifier: Operating System :: MacOS
Classifier: Programming Language :: Python :: 2
Classifier: Programming Language :: Python :: 2.7
Classifier: Programming Language :: Python :: 3
Classifier: Programming Language :: Python :: 3.3
